coxeter3_sage/__init__.py
coxeter3_sage/coxeter3.py
coxeter3_sage-0.0.1.dist-info/LICENSE
coxeter3_sage-0.0.1.dist-info/METADATA
coxeter3_sage-0.0.1.dist-info/WHEEL
coxeter3_sage-0.0.1.dist-info/top_level.txt
coxeter3_sage-0.0.1.dist-info/RECORD
