Metadata-Version: 2.1
Name: coxeter3-sage
Version: 0.0.1
Summary: A simple wrapper around coxeter 3 by Fokko Ducloux which supports arbitrary Coxeter groups.
Home-page: https://github.com/alexbishop/coxeter3-sage
Author: Alex Bishop
Author-email: alexbishop1234@gmail.com
License: UNKNOWN
Project-URL: Bug Tracker, https://github.com/alexbishop/coxeter3-sage/issues
Platform: UNKNOWN
Classifier: Programming Language :: Python :: 3
Classifier: License :: OSI Approved :: MIT License
Classifier: Operating System :: OS Independent
Requires-Python: >=3.6
License-File: LICENSE
